infi.devicemanager-0.2.21-py2.7-nspkg.pth
infi/devicemanager/__init__.py
infi/devicemanager/__version__.py
infi/devicemanager/scripts.py
infi/devicemanager/tests.py
infi/devicemanager/cfgmgr32/__init__.py
infi/devicemanager/ioctl/__init__.py
infi/devicemanager/ioctl/constants.py
infi/devicemanager/ioctl/structures.py
infi/devicemanager/setupapi/__init__.py
infi/devicemanager/setupapi/constants.py
infi/devicemanager/setupapi/functions.py
infi/devicemanager/setupapi/properties.py
infi/devicemanager/setupapi/structures.py
infi/devicemanager/setupapi/tests.py
infi.devicemanager-0.2.21.dist-info/LICENSE
infi.devicemanager-0.2.21.dist-info/METADATA
infi.devicemanager-0.2.21.dist-info/WHEEL
infi.devicemanager-0.2.21.dist-info/entry_points.txt
infi.devicemanager-0.2.21.dist-info/namespace_packages.txt
infi.devicemanager-0.2.21.dist-info/top_level.txt
infi.devicemanager-0.2.21.dist-info/RECORD
